syspilot/__init__.py
syspilot/main.py
syspilot/core/__init__.py
syspilot/core/app.py
syspilot/core/cli.py
syspilot/core/daemon.py
syspilot/platforms/__init__.py
syspilot/platforms/factory.py
syspilot/platforms/linux/__init__.py
syspilot/platforms/linux/cleanup_service.py
syspilot/platforms/linux/monitoring_service.py
syspilot/platforms/linux/system_info_service.py
syspilot/platforms/macos/__init__.py
syspilot/platforms/macos/cleanup_service.py
syspilot/platforms/macos/monitoring_service.py
syspilot/platforms/macos/system_info_service.py
syspilot/platforms/windows/__init__.py
syspilot/platforms/windows/cleanup_service.py
syspilot/platforms/windows/monitoring_service.py
syspilot/platforms/windows/system_info_service.py
syspilot/services/__init__.py
syspilot/services/autostart_service.py
syspilot/services/cleanup_service.py
syspilot/services/monitoring_service.py
syspilot/services/scheduling_service.py
syspilot/services/system_info.py
syspilot/utils/__init__.py
syspilot/utils/config.py
syspilot/utils/logger.py
syspilot/widgets/__init__.py
syspilot/widgets/charts.py
syspilot-1.0.0.data/data/share/applications/syspilot.desktop
syspilot-1.0.0.data/data/share/icons/hicolor/48x48/apps/syspilot_icon.png
syspilot-1.0.0.data/data/share/icons/hicolor/scalable/apps/syspilot_logo.png
syspilot-1.0.0.dist-info/licenses/LICENSE
tests/__init__.py
tests/conftest.py
tests/test_platforms.py
syspilot-1.0.0.dist-info/METADATA
syspilot-1.0.0.dist-info/WHEEL
syspilot-1.0.0.dist-info/entry_points.txt
syspilot-1.0.0.dist-info/top_level.txt
syspilot-1.0.0.dist-info/RECORD
