Metadata-Version: 2.4
Name: syspilot
Version: 1.0.0
Summary: Professional System Automation & Cleanup Tool
Home-page: https://github.com/AFZidan/syspilot
Author: SysPilot Team
Author-email: contact@syspilot.org
Classifier: Development Status :: 5 - Production/Stable
Classifier: Intended Audience :: End Users/Desktop
Classifier: License :: OSI Approved :: MIT License
Classifier: Operating System :: POSIX :: Linux
Classifier: Programming Language :: Python :: 3
Classifier: Programming Language :: Python :: 3.8
Classifier: Programming Language :: Python :: 3.9
Classifier: Programming Language :: Python :: 3.10
Classifier: Programming Language :: Python :: 3.11
Classifier: Topic :: System :: Systems Administration
Classifier: Topic :: Utilities
Requires-Python: >=3.8
License-File: LICENSE
Requires-Dist: psutil>=5.9.0
Requires-Dist: PyQt5>=5.15.0
Requires-Dist: pystray>=0.19.0
Requires-Dist: Pillow>=9.0.0
Requires-Dist: schedule>=1.2.0
Requires-Dist: watchdog>=2.1.0
Requires-Dist: appdirs>=1.4.4
Requires-Dist: configparser>=5.3.0
Requires-Dist: humanize>=4.4.0
Requires-Dist: distro>=1.8.0
Requires-Dist: matplotlib>=3.5.0
Dynamic: author
Dynamic: author-email
Dynamic: classifier
Dynamic: description
Dynamic: description-content-type
Dynamic: home-page
Dynamic: license-file
Dynamic: requires-dist
Dynamic: requires-python
Dynamic: summary
